MANIFEST.in
setup.py
webdav_demo.xml
webdav_setup.xml
webdav_view.xml
./__init__.py
./__openerp__.py
./cache.py
./dav_fs.py
./document_webdav.py
./nodes.py
./redirect.py
./test_davclient.py
./webdav.py
./webdav_server.py
doc/well-known.rst
i18n/ar.po
i18n/bg.po
i18n/ca.po
i18n/cs.po
i18n/da.po
i18n/de.po
i18n/document_webdav.pot
i18n/el.po
i18n/en_GB.po
i18n/es.po
i18n/es_CR.po
i18n/es_EC.po
i18n/es_MX.po
i18n/es_PY.po
i18n/es_VE.po
i18n/et.po
i18n/eu.po
i18n/fi.po
i18n/fr.po
i18n/gl.po
i18n/gu.po
i18n/hr.po
i18n/hu.po
i18n/id.po
i18n/it.po
i18n/ja.po
i18n/mk.po
i18n/mn.po
i18n/nb.po
i18n/nl.po
i18n/pl.po
i18n/pt.po
i18n/pt_BR.po
i18n/ro.po
i18n/ru.po
i18n/sl.po
i18n/sr.po
i18n/sr@latin.po
i18n/sv.po
i18n/tr.po
i18n/zh_CN.po
i18n/zh_TW.po
images/dav_properties.jpeg
images/directories_structure_principals.jpeg
openerp_document_webdav.egg-info/PKG-INFO
openerp_document_webdav.egg-info/SOURCES.txt
openerp_document_webdav.egg-info/dependency_links.txt
openerp_document_webdav.egg-info/requires.txt
openerp_document_webdav.egg-info/top_level.txt
public_html/index.html
security/ir.model.access.csv
test/webdav_test1.yml